langchain/__init__.py
langchain/agents/__init__.py
langchain/agents/agent.py
langchain/agents/agent_toolkits/__init__.py
langchain/agents/agent_toolkits/base.py
langchain/agents/agent_toolkits/csv/__init__.py
langchain/agents/agent_toolkits/csv/base.py
langchain/agents/agent_toolkits/json/__init__.py
langchain/agents/agent_toolkits/json/base.py
langchain/agents/agent_toolkits/json/prompt.py
langchain/agents/agent_toolkits/json/toolkit.py
langchain/agents/agent_toolkits/openapi/__init__.py
langchain/agents/agent_toolkits/openapi/base.py
langchain/agents/agent_toolkits/openapi/prompt.py
langchain/agents/agent_toolkits/openapi/toolkit.py
langchain/agents/agent_toolkits/pandas/__init__.py
langchain/agents/agent_toolkits/pandas/base.py
langchain/agents/agent_toolkits/pandas/prompt.py
langchain/agents/agent_toolkits/python/__init__.py
langchain/agents/agent_toolkits/python/base.py
langchain/agents/agent_toolkits/python/prompt.py
langchain/agents/agent_toolkits/sql/__init__.py
langchain/agents/agent_toolkits/sql/base.py
langchain/agents/agent_toolkits/sql/prompt.py
langchain/agents/agent_toolkits/sql/toolkit.py
langchain/agents/agent_toolkits/vectorstore/__init__.py
langchain/agents/agent_toolkits/vectorstore/base.py
langchain/agents/agent_toolkits/vectorstore/prompt.py
langchain/agents/agent_toolkits/vectorstore/toolkit.py
langchain/agents/conversational/__init__.py
langchain/agents/conversational/base.py
langchain/agents/conversational/prompt.py
langchain/agents/initialize.py
langchain/agents/load_tools.py
langchain/agents/loading.py
langchain/agents/mrkl/__init__.py
langchain/agents/mrkl/base.py
langchain/agents/mrkl/prompt.py
langchain/agents/react/__init__.py
langchain/agents/react/base.py
langchain/agents/react/textworld_prompt.py
langchain/agents/react/wiki_prompt.py
langchain/agents/self_ask_with_search/__init__.py
langchain/agents/self_ask_with_search/base.py
langchain/agents/self_ask_with_search/prompt.py
langchain/agents/tools.py
langchain/cache.py
langchain_ibis-0.0.100.dist-info/LICENSE
langchain_ibis-0.0.100.dist-info/METADATA
langchain_ibis-0.0.100.dist-info/WHEEL
langchain_ibis-0.0.100.dist-info/entry_points.txt
langchain_ibis-0.0.100.dist-info/RECORD
