Metadata-Version: 2.1
Name: langchain-ibis
Version: 0.0.100
Summary: Building applications with LLMs through composability
Home-page: https://www.github.com/hwchase17/langchain
License: MIT
Requires-Python: >=3.8.1,<4.0
Classifier: License :: OSI Approved :: MIT License
Classifier: Programming Language :: Python :: 3
Classifier: Programming Language :: Python :: 3.9
Classifier: Programming Language :: Python :: 3.10
Classifier: Programming Language :: Python :: 3.11
Provides-Extra: all
Provides-Extra: llms
Requires-Dist: PyYAML (>=6,<7)
Requires-Dist: SQLAlchemy (>=1,<2)
Requires-Dist: aiohttp (>=3.8.3,<4.0.0)
Requires-Dist: aleph-alpha-client (>=2.15.0,<3.0.0)
Requires-Dist: anthropic (>=0.2.2,<0.3.0) ; extra == "llms" or extra == "all"
Requires-Dist: beautifulsoup4 (>=4,<5) ; extra == "all"
Requires-Dist: cohere (>=3,<4) ; extra == "llms" or extra == "all"
Requires-Dist: dataclasses-json (>=0.5.7,<0.6.0)
Requires-Dist: deeplake (>=3.2.9,<4.0.0)
Requires-Dist: elasticsearch (>=8,<9) ; extra == "all"
Requires-Dist: faiss-cpu (>=1,<2) ; extra == "all"
Requires-Dist: google-api-python-client (==2.70.0) ; extra == "all"
Requires-Dist: google-search-results (>=2,<3) ; extra == "all"
Requires-Dist: huggingface_hub (>=0,<1) ; extra == "llms" or extra == "all"
Requires-Dist: jinja2 (>=3,<4) ; extra == "all"
Requires-Dist: manifest-ml (>=0.0.1,<0.0.2) ; extra == "llms" or extra == "all"
Requires-Dist: networkx (>=2.6.3,<3.0.0) ; extra == "all"
Requires-Dist: nlpcloud (>=1,<2) ; extra == "llms" or extra == "all"
Requires-Dist: nltk (>=3,<4) ; extra == "all"
Requires-Dist: nomic (>=1.0.43,<2.0.0) ; extra == "all"
Requires-Dist: numpy (>=1,<2)
Requires-Dist: openai (>=0,<1) ; extra == "llms" or extra == "all"
Requires-Dist: opensearch-py (>=2.0.0,<3.0.0) ; extra == "all"
Requires-Dist: pinecone-client (>=2,<3) ; extra == "all"
Requires-Dist: pydantic (>=1,<2)
Requires-Dist: pypdf (>=3.4.0,<4.0.0) ; extra == "all"
Requires-Dist: qdrant-client (>=1.0.4,<2.0.0) ; (python_full_version >= "3.8.1" and python_version < "3.12") and (extra == "all")
Requires-Dist: redis (>=4,<5) ; extra == "all"
Requires-Dist: requests (>=2,<3)
Requires-Dist: sentence-transformers (>=2,<3) ; extra == "all"
Requires-Dist: spacy (>=3,<4) ; extra == "all"
Requires-Dist: tenacity (>=8.1.0,<9.0.0)
Requires-Dist: tensorflow-text (>=2.11.0,<3.0.0) ; (python_version >= "3.10" and python_version < "3.12") and (extra == "all")
Requires-Dist: tiktoken (>=0,<1) ; (python_version >= "3.9" and python_version < "4.0") and (extra == "all")
Requires-Dist: torch (>=1,<2) ; extra == "llms" or extra == "all"
Requires-Dist: transformers (>=4,<5) ; extra == "llms" or extra == "all"
Requires-Dist: weaviate-client (>=3,<4) ; extra == "all"
Requires-Dist: wikipedia (>=1,<2) ; extra == "all"
Requires-Dist: wolframalpha (==5.0.0) ; extra == "all"
Project-URL: Repository, https://www.github.com/hwchase17/langchain
